viaduc/__init__.py
viaduc/viaduc.py
viaduc-2.1.0.dist-info/licenses/LICENSE
viaduc-2.1.0.dist-info/METADATA
viaduc-2.1.0.dist-info/WHEEL
viaduc-2.1.0.dist-info/top_level.txt
viaduc-2.1.0.dist-info/RECORD
