Metadata-Version: 2.4
Name: viaduc
Version: 2.1.0
Summary: probably the simplest way to create a nice-looking gui using python
Home-page: https://github.com/dtmilano/viaduc
Author: Diego Torres Milano
Author-email: dtmilano@gmail.com
License: Apache
Keywords: gui,ui,webview,pywebview,tkinter
License-File: LICENSE
Requires-Dist: argparse
Requires-Dist: pywebview>=5.3.2
Requires-Dist: forbiddenfruit
Dynamic: license-file
